ntcp/icon.gif
ntcp/ntcp.py
ntcp/readme.png
ntcp_1.0-0.1.0.dist-info/DESCRIPTION.rst
ntcp_1.0-0.1.0.dist-info/METADATA
ntcp_1.0-0.1.0.dist-info/RECORD
ntcp_1.0-0.1.0.dist-info/WHEEL
ntcp_1.0-0.1.0.dist-info/entry_points.txt
ntcp_1.0-0.1.0.dist-info/metadata.json
ntcp_1.0-0.1.0.dist-info/top_level.txt
