Metadata-Version: 2.0
Name: ntcp-1.0
Version: 0.1.0
Summary: A Python package to calculate EUD based NTCP.
Home-page: https://github.com/ThirumuruganE/ntcp
Author: Thirumurugan Elango
Author-email: thiru20@protonmail.com
License: GPLv3+
Platform: UNKNOWN
Classifier: License :: OSI Approved :: GNU General Public License v3 or later (GPLv3+)
Classifier: Programming Language :: Python :: 3
Classifier: Programming Language :: Python :: 3.6
Requires-Dist: numpy
Requires-Dist: Cython
Requires-Dist: pandas
Requires-Dist: xlrd
Requires-Dist: matplotlib
Requires-Dist: PrettyTable
